helloworld/__init__.py
cumason123_helloworld-1.0.5.dist-info/METADATA
cumason123_helloworld-1.0.5.dist-info/WHEEL
cumason123_helloworld-1.0.5.dist-info/top_level.txt
cumason123_helloworld-1.0.5.dist-info/RECORD
