Metadata-Version: 2.1
Name: cumason123-helloworld
Version: 1.0.5
Summary: UNKNOWN
Home-page: UNKNOWN
Author: Curtis Mason
Author-email: cumason@bu.edu
License: UNKNOWN
Platform: UNKNOWN
Classifier: License :: OSI Approved :: MIT License
Classifier: Programming Language :: Python :: 3
Classifier: Programming Language :: Python :: 3.8
